odoo/addons/l10n_es_location_nuts/README.rst
odoo/addons/l10n_es_location_nuts/__init__.py
odoo/addons/l10n_es_location_nuts/__manifest__.py
odoo/addons/l10n_es_location_nuts/hooks.py
odoo/addons/l10n_es_location_nuts/i18n/es.po
odoo/addons/l10n_es_location_nuts/i18n/l10n_es_location_nuts.pot
odoo/addons/l10n_es_location_nuts/readme/CONFIGURE.rst
odoo/addons/l10n_es_location_nuts/readme/CONTRIBUTORS.rst
odoo/addons/l10n_es_location_nuts/readme/DESCRIPTION.rst
odoo/addons/l10n_es_location_nuts/readme/USAGE.rst
odoo/addons/l10n_es_location_nuts/static/description/icon.png
odoo/addons/l10n_es_location_nuts/static/description/index.html
odoo/addons/l10n_es_location_nuts/wizard/__init__.py
odoo/addons/l10n_es_location_nuts/wizard/nuts_import.py
odoo12_addon_l10n_es_location_nuts-12.0.1.0.0.99.dev3.dist-info/METADATA
odoo12_addon_l10n_es_location_nuts-12.0.1.0.0.99.dev3.dist-info/WHEEL
odoo12_addon_l10n_es_location_nuts-12.0.1.0.0.99.dev3.dist-info/top_level.txt
odoo12_addon_l10n_es_location_nuts-12.0.1.0.0.99.dev3.dist-info/RECORD
